ballerina_platform_codebleu-0.7.1.dist-info/licenses/LICENSE
codebleu/__init__.py
codebleu/__main__.py
codebleu/bleu.py
codebleu/codebleu.py
codebleu/dataflow_match.py
codebleu/py.typed
codebleu/syntax_match.py
codebleu/utils.py
codebleu/weighted_ngram_match.py
codebleu/keywords/ballerina.txt
codebleu/keywords/c.txt
codebleu/keywords/c_sharp.txt
codebleu/keywords/cpp.txt
codebleu/keywords/go.txt
codebleu/keywords/java.txt
codebleu/keywords/javascript.txt
codebleu/keywords/php.txt
codebleu/keywords/python.txt
codebleu/keywords/ruby.txt
codebleu/keywords/rust.txt
codebleu/parser/DFG.py
codebleu/parser/__init__.py
codebleu/parser/utils.py
ballerina_platform_codebleu-0.7.1.dist-info/METADATA
ballerina_platform_codebleu-0.7.1.dist-info/WHEEL
ballerina_platform_codebleu-0.7.1.dist-info/entry_points.txt
ballerina_platform_codebleu-0.7.1.dist-info/top_level.txt
ballerina_platform_codebleu-0.7.1.dist-info/RECORD
