Metadata-Version: 2.4
Name: ballerina-platform-codebleu
Version: 0.7.1
Summary: Unofficial CodeBLEU implementation that supports Linux, MacOS and Windows available on PyPI.
Author-email: Konstantin Chernyshev <kdchernyshev+github@gmail.com>
License: MIT License
Project-URL: homepage, https://github.com/k4black/codebleu
Keywords: codebleu,code,bleu,nlp,natural language processing,programming,evaluate,evaluation,code generation,metrics
Classifier: Development Status :: 4 - Beta
Classifier: Programming Language :: Python
Classifier: Programming Language :: Python :: 3 :: Only
Classifier: Typing :: Typed
Requires-Python: >=3.9
License-File: LICENSE
Requires-Dist: tree-sitter<0.24.0,>=0.22.0
Requires-Dist: setuptools>=61.0.0
Provides-Extra: all
Requires-Dist: tree-sitter-python~=0.21; extra == "all"
Requires-Dist: tree-sitter-go~=0.21; extra == "all"
Requires-Dist: tree-sitter-javascript~=0.21; extra == "all"
Requires-Dist: tree-sitter-ruby~=0.21; extra == "all"
Requires-Dist: tree-sitter-php~=0.22; extra == "all"
Requires-Dist: tree-sitter-java~=0.21; extra == "all"
Requires-Dist: tree-sitter-c-sharp~=0.21; extra == "all"
Requires-Dist: tree-sitter-c~=0.21; extra == "all"
Requires-Dist: tree-sitter-cpp~=0.22; extra == "all"
Requires-Dist: tree-sitter-rust~=0.21; extra == "all"
Requires-Dist: tree-sitter-ballerina~=0.1.0; extra == "all"
Provides-Extra: test
Requires-Dist: pytest<9.0.0,>=7.0.0; extra == "test"
Requires-Dist: pytest-cov<7.0.0,>=4.0.0; extra == "test"
Requires-Dist: pytest-mock<4.0.0,>=3.0.0; extra == "test"
Requires-Dist: pytest-timeout<3.0.0,>=2.0.0; extra == "test"
Requires-Dist: black==24.10.0; extra == "test"
Requires-Dist: mypy<2.0.0,>=1.0.0; extra == "test"
Requires-Dist: types-tree-sitter; extra == "test"
Requires-Dist: flake8<8.0.0,>=6.0.0; extra == "test"
Requires-Dist: ruff<0.10.0,>=0.5.1; extra == "test"
Requires-Dist: isort<6.0.0,>=5.0.0; extra == "test"
Requires-Dist: nltk<4.0.0,>=3.0.0; extra == "test"
Dynamic: license-file
